<?xml version="1.0" encoding="UTF-8" standalone="no"?>
<DIAGRAMA ID="1" TIPO="tpConceitual" UniversalUnicID="33FC-96-39E8-64-6319-6D-55">
    <InfoDiagrama ID="1">
        <Versao Valor="3.2.0"/>
        <Autores/>
        <Observacao/>
        <Width Valor="4096"/>
        <Height Valor="4096"/>
        <Alinhamento_v Valor="50"/>
        <Alinhamento_h Valor="60"/>
        <Zoom Valor="100"/>
        <Fonte Estilo="1" Nome="Arial" Tamanho="12"/>
        <Localizacao Left="306" Top="279"/>
        <Realce Valor="false"/>
    </InfoDiagrama>
    <Entidade ID="2">
        <Bounds Height="58" Left="415" Top="316" Width="120"/>
        <DisablePainted Valor="false"/>
        <Texto>Usuario</Texto>
        <Observacao/>
        <Dicionario/>
        <Fonte Estilo="1" Nome="Arial" Tamanho="12"/>
        <Ancorado Valor="false"/>
        <AtributosOcultos Valor=""/>
    </Entidade>
    <Entidade ID="3">
        <Bounds Height="58" Left="774" Top="318" Width="120"/>
        <DisablePainted Valor="false"/>
        <Texto>Viagem</Texto>
        <Observacao/>
        <Dicionario/>
        <Fonte Estilo="1" Nome="Arial" Tamanho="12"/>
        <Ancorado Valor="false"/>
        <AtributosOcultos Valor=""/>
    </Entidade>
    <Entidade ID="4">
        <Bounds Height="58" Left="810" Top="529" Width="120"/>
        <DisablePainted Valor="false"/>
        <Texto>Local</Texto>
        <Observacao/>
        <Dicionario/>
        <Fonte Estilo="1" Nome="Arial" Tamanho="12"/>
        <Ancorado Valor="false"/>
        <AtributosOcultos Valor=""/>
    </Entidade>
    <Entidade ID="10">
        <Bounds Height="58" Left="418" Top="418" Width="120"/>
        <DisablePainted Valor="false"/>
        <Texto>Despesas</Texto>
        <Observacao/>
        <Dicionario/>
        <Fonte Estilo="1" Nome="Arial" Tamanho="12"/>
        <Ancorado Valor="false"/>
        <AtributosOcultos Valor=""/>
    </Entidade>
    <Atributo ID="12">
        <Bounds Height="14" Left="431" Top="282" Width="85"/>
        <DisablePainted Valor="false"/>
        <Texto>ID_Usuario</Texto>
        <Observacao/>
        <Dicionario/>
        <Fonte Estilo="1" Nome="Arial" Tamanho="12"/>
        <Ancorado Valor="false"/>
        <DirecaoFromInspector Valor="0"/>
        <Autosize Valor="true"/>
        <Identificador Valor="true"/>
        <Opcional Valor="false"/>
        <Multivalorado Valor="false"/>
        <CardMinFromString Valor="1"/>
        <CardMaxFromString Valor="n"/>
        <TipoAtributo Valor=""/>
    </Atributo>
    <Ligacao ID="13">
        <DisablePainted Valor="false"/>
        <Tag LinhaMestre="-1"/>
        <Dashed Valor="false"/>
        <Ancorado Valor="false"/>
        <TemSetaPontaA Valor="false"/>
        <TemSetaPontaB Valor="false"/>
        <SetaAberta Valor="true"/>
        <SetaLargura Valor="10"/>
        <Inteligente Valor="true"/>
        <Largura Valor="1"/>
        <Ligacoes PontaA="12" PontaB="2"/>
        <Pontos>
            <Ponto Left="428" Top="286"/>
            <Ponto Left="418" Top="286"/>
            <Ponto Left="418" Top="312"/>
        </Pontos>
    </Ligacao>
    <Atributo ID="16">
        <Bounds Height="14" Left="340" Top="329" Width="35"/>
        <DisablePainted Valor="false"/>
        <Texto>IG</Texto>
        <Observacao/>
        <Dicionario/>
        <Fonte Estilo="1" Nome="Arial" Tamanho="12"/>
        <Ancorado Valor="false"/>
        <DirecaoFromInspector Valor="1"/>
        <Autosize Valor="true"/>
        <Identificador Valor="false"/>
        <Opcional Valor="false"/>
        <Multivalorado Valor="false"/>
        <CardMinFromString Valor="1"/>
        <CardMaxFromString Valor="n"/>
        <TipoAtributo Valor=""/>
    </Atributo>
    <Ligacao ID="17">
        <DisablePainted Valor="false"/>
        <Tag LinhaMestre="-1"/>
        <Dashed Valor="false"/>
        <Ancorado Valor="false"/>
        <TemSetaPontaA Valor="false"/>
        <TemSetaPontaB Valor="false"/>
        <SetaAberta Valor="true"/>
        <SetaLargura Valor="10"/>
        <Inteligente Valor="true"/>
        <Largura Valor="1"/>
        <Ligacoes PontaA="16" PontaB="2"/>
        <Pontos>
            <Ponto Left="372" Top="333"/>
            <Ponto Left="392" Top="333"/>
            <Ponto Left="392" Top="333"/>
            <Ponto Left="411" Top="333"/>
        </Pontos>
    </Ligacao>
    <Atributo ID="21">
        <Bounds Height="14" Left="320" Top="350" Width="55"/>
        <DisablePainted Valor="false"/>
        <Texto>Email</Texto>
        <Observacao/>
        <Dicionario/>
        <Fonte Estilo="1" Nome="Arial" Tamanho="12"/>
        <Ancorado Valor="false"/>
        <DirecaoFromInspector Valor="1"/>
        <Autosize Valor="true"/>
        <Identificador Valor="false"/>
        <Opcional Valor="false"/>
        <Multivalorado Valor="false"/>
        <CardMinFromString Valor="1"/>
        <CardMaxFromString Valor="n"/>
        <TipoAtributo Valor=""/>
    </Atributo>
    <Ligacao ID="22">
        <DisablePainted Valor="false"/>
        <Tag LinhaMestre="-1"/>
        <Dashed Valor="false"/>
        <Ancorado Valor="false"/>
        <TemSetaPontaA Valor="false"/>
        <TemSetaPontaB Valor="false"/>
        <SetaAberta Valor="true"/>
        <SetaLargura Valor="10"/>
        <Inteligente Valor="true"/>
        <Largura Valor="1"/>
        <Ligacoes PontaA="21" PontaB="2"/>
        <Pontos>
            <Ponto Left="372" Top="354"/>
            <Ponto Left="392" Top="354"/>
            <Ponto Left="392" Top="354"/>
            <Ponto Left="411" Top="354"/>
        </Pontos>
    </Ligacao>
    <Atributo ID="27">
        <Bounds Height="14" Left="934" Top="334" Width="55"/>
        <DisablePainted Valor="false"/>
        <Texto>Titulo</Texto>
        <Observacao/>
        <Dicionario/>
        <Fonte Estilo="1" Nome="Arial" Tamanho="12"/>
        <Ancorado Valor="false"/>
        <DirecaoFromInspector Valor="0"/>
        <Autosize Valor="true"/>
        <Identificador Valor="false"/>
        <Opcional Valor="false"/>
        <Multivalorado Valor="false"/>
        <CardMinFromString Valor="1"/>
        <CardMaxFromString Valor="n"/>
        <TipoAtributo Valor=""/>
    </Atributo>
    <Ligacao ID="28">
        <DisablePainted Valor="false"/>
        <Tag LinhaMestre="-1"/>
        <Dashed Valor="false"/>
        <Ancorado Valor="false"/>
        <TemSetaPontaA Valor="false"/>
        <TemSetaPontaB Valor="false"/>
        <SetaAberta Valor="true"/>
        <SetaLargura Valor="10"/>
        <Inteligente Valor="true"/>
        <Largura Valor="1"/>
        <Ligacoes PontaA="27" PontaB="3"/>
        <Pontos>
            <Ponto Left="931" Top="338"/>
            <Ponto Left="911" Top="338"/>
            <Ponto Left="911" Top="338"/>
            <Ponto Left="891" Top="338"/>
        </Pontos>
    </Ligacao>
    <Atributo ID="29">
        <Bounds Height="14" Left="934" Top="319" Width="67"/>
        <DisablePainted Valor="false"/>
        <Texto>Destino</Texto>
        <Observacao/>
        <Dicionario/>
        <Fonte Estilo="1" Nome="Arial" Tamanho="12"/>
        <Ancorado Valor="false"/>
        <DirecaoFromInspector Valor="0"/>
        <Autosize Valor="true"/>
        <Identificador Valor="false"/>
        <Opcional Valor="false"/>
        <Multivalorado Valor="false"/>
        <CardMinFromString Valor="1"/>
        <CardMaxFromString Valor="n"/>
        <TipoAtributo Valor=""/>
    </Atributo>
    <Ligacao ID="30">
        <DisablePainted Valor="false"/>
        <Tag LinhaMestre="-1"/>
        <Dashed Valor="false"/>
        <Ancorado Valor="false"/>
        <TemSetaPontaA Valor="false"/>
        <TemSetaPontaB Valor="false"/>
        <SetaAberta Valor="true"/>
        <SetaLargura Valor="10"/>
        <Inteligente Valor="true"/>
        <Largura Valor="1"/>
        <Ligacoes PontaA="29" PontaB="3"/>
        <Pontos>
            <Ponto Left="931" Top="323"/>
            <Ponto Left="911" Top="323"/>
            <Ponto Left="911" Top="323"/>
            <Ponto Left="891" Top="323"/>
        </Pontos>
    </Ligacao>
    <Atributo ID="31">
        <Bounds Height="14" Left="934" Top="347" Width="86"/>
        <DisablePainted Valor="false"/>
        <Texto>Data_Inicio</Texto>
        <Observacao/>
        <Dicionario/>
        <Fonte Estilo="1" Nome="Arial" Tamanho="12"/>
        <Ancorado Valor="false"/>
        <DirecaoFromInspector Valor="0"/>
        <Autosize Valor="true"/>
        <Identificador Valor="false"/>
        <Opcional Valor="false"/>
        <Multivalorado Valor="false"/>
        <CardMinFromString Valor="1"/>
        <CardMaxFromString Valor="n"/>
        <TipoAtributo Valor=""/>
    </Atributo>
    <Ligacao ID="32">
        <DisablePainted Valor="false"/>
        <Tag LinhaMestre="-1"/>
        <Dashed Valor="false"/>
        <Ancorado Valor="false"/>
        <TemSetaPontaA Valor="false"/>
        <TemSetaPontaB Valor="false"/>
        <SetaAberta Valor="true"/>
        <SetaLargura Valor="10"/>
        <Inteligente Valor="true"/>
        <Largura Valor="1"/>
        <Ligacoes PontaA="31" PontaB="3"/>
        <Pontos>
            <Ponto Left="931" Top="351"/>
            <Ponto Left="911" Top="351"/>
            <Ponto Left="911" Top="351"/>
            <Ponto Left="891" Top="351"/>
        </Pontos>
    </Ligacao>
    <Atributo ID="33">
        <Bounds Height="14" Left="934" Top="361" Width="100"/>
        <DisablePainted Valor="false"/>
        <Texto>Data_termino</Texto>
        <Observacao/>
        <Dicionario/>
        <Fonte Estilo="1" Nome="Arial" Tamanho="12"/>
        <Ancorado Valor="false"/>
        <DirecaoFromInspector Valor="0"/>
        <Autosize Valor="true"/>
        <Identificador Valor="false"/>
        <Opcional Valor="false"/>
        <Multivalorado Valor="false"/>
        <CardMinFromString Valor="1"/>
        <CardMaxFromString Valor="n"/>
        <TipoAtributo Valor=""/>
    </Atributo>
    <Ligacao ID="34">
        <DisablePainted Valor="false"/>
        <Tag LinhaMestre="-1"/>
        <Dashed Valor="false"/>
        <Ancorado Valor="false"/>
        <TemSetaPontaA Valor="false"/>
        <TemSetaPontaB Valor="false"/>
        <SetaAberta Valor="true"/>
        <SetaLargura Valor="10"/>
        <Inteligente Valor="true"/>
        <Largura Valor="1"/>
        <Ligacoes PontaA="33" PontaB="3"/>
        <Pontos>
            <Ponto Left="931" Top="365"/>
            <Ponto Left="911" Top="365"/>
            <Ponto Left="911" Top="365"/>
            <Ponto Left="891" Top="365"/>
        </Pontos>
    </Ligacao>
    <Atributo ID="51">
        <Bounds Height="14" Left="970" Top="529" Width="57"/>
        <DisablePainted Valor="false"/>
        <Texto>Nome</Texto>
        <Observacao/>
        <Dicionario/>
        <Fonte Estilo="1" Nome="Arial" Tamanho="12"/>
        <Ancorado Valor="false"/>
        <DirecaoFromInspector Valor="0"/>
        <Autosize Valor="true"/>
        <Identificador Valor="false"/>
        <Opcional Valor="false"/>
        <Multivalorado Valor="false"/>
        <CardMinFromString Valor="1"/>
        <CardMaxFromString Valor="n"/>
        <TipoAtributo Valor=""/>
    </Atributo>
    <Ligacao ID="52">
        <DisablePainted Valor="false"/>
        <Tag LinhaMestre="-1"/>
        <Dashed Valor="false"/>
        <Ancorado Valor="false"/>
        <TemSetaPontaA Valor="false"/>
        <TemSetaPontaB Valor="false"/>
        <SetaAberta Valor="true"/>
        <SetaLargura Valor="10"/>
        <Inteligente Valor="true"/>
        <Largura Valor="1"/>
        <Ligacoes PontaA="4" PontaB="51"/>
        <Pontos>
            <Ponto Left="927" Top="533"/>
            <Ponto Left="947" Top="533"/>
            <Ponto Left="947" Top="533"/>
            <Ponto Left="967" Top="533"/>
        </Pontos>
    </Ligacao>
    <Atributo ID="53">
        <Bounds Height="14" Left="970" Top="547" Width="63"/>
        <DisablePainted Valor="false"/>
        <Texto>Cidade</Texto>
        <Observacao/>
        <Dicionario/>
        <Fonte Estilo="1" Nome="Arial" Tamanho="12"/>
        <Ancorado Valor="false"/>
        <DirecaoFromInspector Valor="0"/>
        <Autosize Valor="true"/>
        <Identificador Valor="false"/>
        <Opcional Valor="false"/>
        <Multivalorado Valor="false"/>
        <CardMinFromString Valor="1"/>
        <CardMaxFromString Valor="n"/>
        <TipoAtributo Valor=""/>
    </Atributo>
    <Ligacao ID="54">
        <DisablePainted Valor="false"/>
        <Tag LinhaMestre="-1"/>
        <Dashed Valor="false"/>
        <Ancorado Valor="false"/>
        <TemSetaPontaA Valor="false"/>
        <TemSetaPontaB Valor="false"/>
        <SetaAberta Valor="true"/>
        <SetaLargura Valor="10"/>
        <Inteligente Valor="true"/>
        <Largura Valor="1"/>
        <Ligacoes PontaA="53" PontaB="4"/>
        <Pontos>
            <Ponto Left="967" Top="551"/>
            <Ponto Left="947" Top="551"/>
            <Ponto Left="947" Top="551"/>
            <Ponto Left="927" Top="551"/>
        </Pontos>
    </Ligacao>
    <Entidade ID="56">
        <Bounds Height="58" Left="813" Top="727" Width="120"/>
        <DisablePainted Valor="false"/>
        <Texto>Tipo</Texto>
        <Observacao/>
        <Dicionario/>
        <Fonte Estilo="1" Nome="Arial" Tamanho="12"/>
        <Ancorado Valor="false"/>
        <AtributosOcultos Valor=""/>
    </Entidade>
    <Especializacao ID="57">
        <Bounds Height="32" Left="851" Top="814" Width="40"/>
        <DisablePainted Valor="false"/>
        <Texto>Especialização_1</Texto>
        <Observacao/>
        <Dicionario/>
        <Fonte Estilo="1" Nome="Arial" Tamanho="12"/>
        <Ancorado Valor="false"/>
        <Direcao Valor="0"/>
        <Ocupado01 ID="57"/>
        <Ocupado02 ID="57"/>
        <Ocupado03 ID="57"/>
        <Parcial Valor="false"/>
    </Especializacao>
    <Ligacao ID="58">
        <DisablePainted Valor="false"/>
        <Tag LinhaMestre="-1"/>
        <Dashed Valor="false"/>
        <Ancorado Valor="false"/>
        <TemSetaPontaA Valor="false"/>
        <TemSetaPontaB Valor="false"/>
        <SetaAberta Valor="true"/>
        <SetaLargura Valor="10"/>
        <Inteligente Valor="false"/>
        <Largura Valor="1"/>
        <Ligacoes PontaA="56" PontaB="57"/>
        <Pontos>
            <Ponto Left="867" Top="782"/>
            <Ponto Left="868" Top="811"/>
        </Pontos>
    </Ligacao>
    <Entidade ID="59">
        <Bounds Height="58" Left="689" Top="864" Width="120"/>
        <DisablePainted Valor="false"/>
        <Texto>Praia</Texto>
        <Observacao/>
        <Dicionario/>
        <Fonte Estilo="1" Nome="Arial" Tamanho="12"/>
        <Ancorado Valor="false"/>
        <AtributosOcultos Valor=""/>
    </Entidade>
    <Ligacao ID="60">
        <DisablePainted Valor="false"/>
        <Tag LinhaMestre="-1"/>
        <Dashed Valor="false"/>
        <Ancorado Valor="false"/>
        <TemSetaPontaA Valor="false"/>
        <TemSetaPontaB Valor="false"/>
        <SetaAberta Valor="true"/>
        <SetaLargura Valor="10"/>
        <Inteligente Valor="false"/>
        <Largura Valor="1"/>
        <Ligacoes PontaA="57" PontaB="59"/>
        <Pontos>
            <Ponto Left="848" Top="843"/>
            <Ponto Left="794" Top="860"/>
        </Pontos>
    </Ligacao>
    <Entidade ID="62">
        <Bounds Height="58" Left="817" Top="866" Width="120"/>
        <DisablePainted Valor="false"/>
        <Texto>Museu</Texto>
        <Observacao/>
        <Dicionario/>
        <Fonte Estilo="1" Nome="Arial" Tamanho="12"/>
        <Ancorado Valor="false"/>
        <AtributosOcultos Valor=""/>
    </Entidade>
    <Entidade ID="63">
        <Bounds Height="58" Left="942" Top="867" Width="120"/>
        <DisablePainted Valor="false"/>
        <Texto> Bar</Texto>
        <Observacao/>
        <Dicionario/>
        <Fonte Estilo="1" Nome="Arial" Tamanho="12"/>
        <Ancorado Valor="false"/>
        <AtributosOcultos Valor=""/>
    </Entidade>
    <Ligacao ID="64">
        <DisablePainted Valor="false"/>
        <Tag LinhaMestre="-1"/>
        <Dashed Valor="false"/>
        <Ancorado Valor="false"/>
        <TemSetaPontaA Valor="false"/>
        <TemSetaPontaB Valor="false"/>
        <SetaAberta Valor="true"/>
        <SetaLargura Valor="10"/>
        <Inteligente Valor="false"/>
        <Largura Valor="1"/>
        <Ligacoes PontaA="57" PontaB="62"/>
        <Pontos>
            <Ponto Left="868" Top="843"/>
            <Ponto Left="869" Top="862"/>
        </Pontos>
    </Ligacao>
    <Ligacao ID="65">
        <DisablePainted Valor="false"/>
        <Tag LinhaMestre="-1"/>
        <Dashed Valor="false"/>
        <Ancorado Valor="false"/>
        <TemSetaPontaA Valor="false"/>
        <TemSetaPontaB Valor="false"/>
        <SetaAberta Valor="true"/>
        <SetaLargura Valor="10"/>
        <Inteligente Valor="false"/>
        <Largura Valor="1"/>
        <Ligacoes PontaA="57" PontaB="63"/>
        <Pontos>
            <Ponto Left="888" Top="843"/>
            <Ponto Left="958" Top="863"/>
        </Pontos>
    </Ligacao>
    <Ligacao ID="68">
        <DisablePainted Valor="false"/>
        <Tag LinhaMestre="-1"/>
        <Dashed Valor="false"/>
        <Ancorado Valor="false"/>
        <TemSetaPontaA Valor="false"/>
        <TemSetaPontaB Valor="false"/>
        <SetaAberta Valor="true"/>
        <SetaLargura Valor="10"/>
        <Inteligente Valor="true"/>
        <Largura Valor="1"/>
        <Ligacoes PontaA="69" PontaB="4"/>
        <Pontos>
            <Ponto Left="867" Top="632"/>
            <Ponto Left="867" Top="608"/>
            <Ponto Left="867" Top="608"/>
            <Ponto Left="867" Top="584"/>
        </Pontos>
        <Cardinalidade ID="70">
            <Bounds Height="14" Left="834" Top="594" Width="35"/>
            <DisablePainted Valor="false"/>
            <Texto>Cardinalidade_1</Texto>
            <Observacao/>
            <Dicionario/>
            <Fonte Estilo="1" Nome="Arial" Tamanho="12"/>
            <Ancorado Valor="false"/>
            <TamanhoAutmatico Valor="true"/>
            <Card Valor="2"/>
            <MovimentacaoManual Valor="false"/>
            <Papel Valor=""/>
        </Cardinalidade>
    </Ligacao>
    <Relacionamento ID="69">
        <Bounds Height="50" Left="795" Top="635" Width="150"/>
        <DisablePainted Valor="false"/>
        <Texto>Possui</Texto>
        <Observacao/>
        <Dicionario/>
        <Fonte Estilo="1" Nome="Arial" Tamanho="12"/>
        <Ancorado Valor="false"/>
    </Relacionamento>
    <Ligacao ID="71">
        <DisablePainted Valor="false"/>
        <Tag LinhaMestre="-1"/>
        <Dashed Valor="false"/>
        <Ancorado Valor="false"/>
        <TemSetaPontaA Valor="false"/>
        <TemSetaPontaB Valor="false"/>
        <SetaAberta Valor="true"/>
        <SetaLargura Valor="10"/>
        <Inteligente Valor="true"/>
        <Largura Valor="1"/>
        <Ligacoes PontaA="56" PontaB="69"/>
        <Pontos>
            <Ponto Left="867" Top="723"/>
            <Ponto Left="867" Top="703"/>
            <Ponto Left="867" Top="703"/>
            <Ponto Left="867" Top="682"/>
        </Pontos>
        <Cardinalidade ID="72">
            <Bounds Height="14" Left="834" Top="705" Width="35"/>
            <DisablePainted Valor="false"/>
            <Texto>Cardinalidade_2</Texto>
            <Observacao/>
            <Dicionario/>
            <Fonte Estilo="1" Nome="Arial" Tamanho="12"/>
            <Ancorado Valor="false"/>
            <TamanhoAutmatico Valor="true"/>
            <Card Valor="0"/>
            <MovimentacaoManual Valor="false"/>
            <Papel Valor=""/>
        </Cardinalidade>
    </Ligacao>
    <Atributo ID="81">
        <Bounds Height="14" Left="921" Top="495" Width="72"/>
        <DisablePainted Valor="false"/>
        <Texto>ID_Local</Texto>
        <Observacao/>
        <Dicionario/>
        <Fonte Estilo="1" Nome="Arial" Tamanho="12"/>
        <Ancorado Valor="false"/>
        <DirecaoFromInspector Valor="0"/>
        <Autosize Valor="true"/>
        <Identificador Valor="true"/>
        <Opcional Valor="false"/>
        <Multivalorado Valor="false"/>
        <CardMinFromString Valor="1"/>
        <CardMaxFromString Valor="n"/>
        <TipoAtributo Valor=""/>
    </Atributo>
    <Ligacao ID="82">
        <DisablePainted Valor="false"/>
        <Tag LinhaMestre="-1"/>
        <Dashed Valor="false"/>
        <Ancorado Valor="false"/>
        <TemSetaPontaA Valor="false"/>
        <TemSetaPontaB Valor="false"/>
        <SetaAberta Valor="true"/>
        <SetaLargura Valor="10"/>
        <Inteligente Valor="true"/>
        <Largura Valor="1"/>
        <Ligacoes PontaA="4" PontaB="81"/>
        <Pontos>
            <Ponto Left="908" Top="525"/>
            <Ponto Left="908" Top="516"/>
            <Ponto Left="908" Top="516"/>
            <Ponto Left="908" Top="499"/>
            <Ponto Left="917" Top="499"/>
        </Pontos>
    </Ligacao>
    <Atributo ID="86">
        <Bounds Height="14" Left="793" Top="283" Width="85"/>
        <DisablePainted Valor="false"/>
        <Texto>ID_Viagem</Texto>
        <Observacao/>
        <Dicionario/>
        <Fonte Estilo="1" Nome="Arial" Tamanho="12"/>
        <Ancorado Valor="false"/>
        <DirecaoFromInspector Valor="0"/>
        <Autosize Valor="true"/>
        <Identificador Valor="true"/>
        <Opcional Valor="false"/>
        <Multivalorado Valor="false"/>
        <CardMinFromString Valor="1"/>
        <CardMaxFromString Valor="n"/>
        <TipoAtributo Valor=""/>
    </Atributo>
    <Ligacao ID="87">
        <DisablePainted Valor="false"/>
        <Tag LinhaMestre="-1"/>
        <Dashed Valor="false"/>
        <Ancorado Valor="false"/>
        <TemSetaPontaA Valor="false"/>
        <TemSetaPontaB Valor="false"/>
        <SetaAberta Valor="true"/>
        <SetaLargura Valor="10"/>
        <Inteligente Valor="true"/>
        <Largura Valor="1"/>
        <Ligacoes PontaA="86" PontaB="3"/>
        <Pontos>
            <Ponto Left="789" Top="287"/>
            <Ponto Left="780" Top="287"/>
            <Ponto Left="780" Top="304"/>
            <Ponto Left="780" Top="304"/>
            <Ponto Left="780" Top="314"/>
        </Pontos>
    </Ligacao>
    <EntidadeAssociativa ID="97">
        <Bounds Height="58" Left="573" Top="317" Width="158"/>
        <DisablePainted Valor="false"/>
        <Texto>Avaliacao</Texto>
        <Observacao/>
        <Dicionario/>
        <Fonte Estilo="1" Nome="Arial" Tamanho="12"/>
        <Ancorado Valor="false"/>
        <AtributosOcultos Valor=""/>
        <Relacionamento ID="96">
            <DisablePainted Valor="false"/>
            <Texto>Faz</Texto>
            <Observacao/>
            <Dicionario/>
            <Fonte Estilo="1" Nome="Arial" Tamanho="12"/>
            <Ancorado Valor="false"/>
        </Relacionamento>
    </EntidadeAssociativa>
    <Ligacao ID="99">
        <DisablePainted Valor="false"/>
        <Tag LinhaMestre="-1"/>
        <Dashed Valor="false"/>
        <Ancorado Valor="false"/>
        <TemSetaPontaA Valor="false"/>
        <TemSetaPontaB Valor="false"/>
        <SetaAberta Valor="true"/>
        <SetaLargura Valor="10"/>
        <Inteligente Valor="true"/>
        <Largura Valor="1"/>
        <Ligacoes PontaA="96" PontaB="2"/>
        <Pontos>
            <Ponto Left="578" Top="342"/>
            <Ponto Left="551" Top="342"/>
            <Ponto Left="551" Top="342"/>
            <Ponto Left="532" Top="342"/>
        </Pontos>
        <Cardinalidade ID="100">
            <Bounds Height="14" Left="542" Top="330" Width="35"/>
            <DisablePainted Valor="false"/>
            <Texto>Cardinalidade_3</Texto>
            <Observacao/>
            <Dicionario/>
            <Fonte Estilo="1" Nome="Arial" Tamanho="12"/>
            <Ancorado Valor="false"/>
            <TamanhoAutmatico Valor="true"/>
            <Card Valor="0"/>
            <MovimentacaoManual Valor="false"/>
            <Papel Valor=""/>
        </Cardinalidade>
    </Ligacao>
    <Ligacao ID="101">
        <DisablePainted Valor="false"/>
        <Tag LinhaMestre="-1"/>
        <Dashed Valor="false"/>
        <Ancorado Valor="false"/>
        <TemSetaPontaA Valor="false"/>
        <TemSetaPontaB Valor="false"/>
        <SetaAberta Valor="true"/>
        <SetaLargura Valor="10"/>
        <Inteligente Valor="true"/>
        <Largura Valor="1"/>
        <Ligacoes PontaA="96" PontaB="3"/>
        <Pontos>
            <Ponto Left="718" Top="342"/>
            <Ponto Left="749" Top="342"/>
            <Ponto Left="749" Top="342"/>
            <Ponto Left="770" Top="342"/>
        </Pontos>
        <Cardinalidade ID="102">
            <Bounds Height="14" Left="731" Top="330" Width="35"/>
            <DisablePainted Valor="false"/>
            <Texto>Cardinalidade_4</Texto>
            <Observacao/>
            <Dicionario/>
            <Fonte Estilo="1" Nome="Arial" Tamanho="12"/>
            <Ancorado Valor="false"/>
            <TamanhoAutmatico Valor="true"/>
            <Card Valor="2"/>
            <MovimentacaoManual Valor="false"/>
            <Papel Valor=""/>
        </Cardinalidade>
    </Ligacao>
    <Ligacao ID="112">
        <DisablePainted Valor="false"/>
        <Tag LinhaMestre="-1"/>
        <Dashed Valor="false"/>
        <Ancorado Valor="false"/>
        <TemSetaPontaA Valor="false"/>
        <TemSetaPontaB Valor="false"/>
        <SetaAberta Valor="true"/>
        <SetaLargura Valor="10"/>
        <Inteligente Valor="true"/>
        <Largura Valor="1"/>
        <Ligacoes PontaA="113" PontaB="3"/>
        <Pontos>
            <Ponto Left="870" Top="426"/>
            <Ponto Left="870" Top="399"/>
            <Ponto Left="870" Top="399"/>
            <Ponto Left="870" Top="373"/>
        </Pontos>
        <Cardinalidade ID="114">
            <Bounds Height="14" Left="837" Top="383" Width="35"/>
            <DisablePainted Valor="false"/>
            <Texto>Cardinalidade_5</Texto>
            <Observacao/>
            <Dicionario/>
            <Fonte Estilo="1" Nome="Arial" Tamanho="12"/>
            <Ancorado Valor="false"/>
            <TamanhoAutmatico Valor="true"/>
            <Card Valor="2"/>
            <MovimentacaoManual Valor="false"/>
            <Papel Valor=""/>
        </Cardinalidade>
    </Ligacao>
    <Relacionamento ID="113">
        <Bounds Height="50" Left="798" Top="429" Width="150"/>
        <DisablePainted Valor="false"/>
        <Texto>Possui</Texto>
        <Observacao/>
        <Dicionario/>
        <Fonte Estilo="1" Nome="Arial" Tamanho="12"/>
        <Ancorado Valor="false"/>
    </Relacionamento>
    <Ligacao ID="115">
        <DisablePainted Valor="false"/>
        <Tag LinhaMestre="-1"/>
        <Dashed Valor="false"/>
        <Ancorado Valor="false"/>
        <TemSetaPontaA Valor="false"/>
        <TemSetaPontaB Valor="false"/>
        <SetaAberta Valor="true"/>
        <SetaLargura Valor="10"/>
        <Inteligente Valor="true"/>
        <Largura Valor="1"/>
        <Ligacoes PontaA="4" PontaB="113"/>
        <Pontos>
            <Ponto Left="870" Top="525"/>
            <Ponto Left="870" Top="501"/>
            <Ponto Left="870" Top="501"/>
            <Ponto Left="870" Top="476"/>
        </Pontos>
        <Cardinalidade ID="116">
            <Bounds Height="14" Left="837" Top="507" Width="35"/>
            <DisablePainted Valor="false"/>
            <Texto>Cardinalidade_6</Texto>
            <Observacao/>
            <Dicionario/>
            <Fonte Estilo="1" Nome="Arial" Tamanho="12"/>
            <Ancorado Valor="false"/>
            <TamanhoAutmatico Valor="true"/>
            <Card Valor="2"/>
            <MovimentacaoManual Valor="false"/>
            <Papel Valor=""/>
        </Cardinalidade>
    </Ligacao>
    <Ligacao ID="125">
        <DisablePainted Valor="false"/>
        <Tag LinhaMestre="-1"/>
        <Dashed Valor="false"/>
        <Ancorado Valor="false"/>
        <TemSetaPontaA Valor="false"/>
        <TemSetaPontaB Valor="false"/>
        <SetaAberta Valor="true"/>
        <SetaLargura Valor="10"/>
        <Inteligente Valor="true"/>
        <Largura Valor="1"/>
        <Ligacoes PontaA="126" PontaB="3"/>
        <Pontos>
            <Ponto Left="723" Top="443"/>
            <Ponto Left="747" Top="443"/>
            <Ponto Left="747" Top="365"/>
            <Ponto Left="770" Top="365"/>
        </Pontos>
        <Cardinalidade ID="127">
            <Bounds Height="14" Left="731" Top="353" Width="35"/>
            <DisablePainted Valor="false"/>
            <Texto>Cardinalidade_7</Texto>
            <Observacao/>
            <Dicionario/>
            <Fonte Estilo="1" Nome="Arial" Tamanho="12"/>
            <Ancorado Valor="false"/>
            <TamanhoAutmatico Valor="true"/>
            <Card Valor="0"/>
            <MovimentacaoManual Valor="false"/>
            <Papel Valor=""/>
        </Cardinalidade>
    </Ligacao>
    <Relacionamento ID="126">
        <Bounds Height="50" Left="576" Top="421" Width="150"/>
        <DisablePainted Valor="false"/>
        <Texto>Tem</Texto>
        <Observacao/>
        <Dicionario/>
        <Fonte Estilo="1" Nome="Arial" Tamanho="12"/>
        <Ancorado Valor="false"/>
    </Relacionamento>
    <Ligacao ID="128">
        <DisablePainted Valor="false"/>
        <Tag LinhaMestre="-1"/>
        <Dashed Valor="false"/>
        <Ancorado Valor="false"/>
        <TemSetaPontaA Valor="false"/>
        <TemSetaPontaB Valor="false"/>
        <SetaAberta Valor="true"/>
        <SetaLargura Valor="10"/>
        <Inteligente Valor="true"/>
        <Largura Valor="1"/>
        <Ligacoes PontaA="10" PontaB="126"/>
        <Pontos>
            <Ponto Left="535" Top="443"/>
            <Ponto Left="554" Top="443"/>
            <Ponto Left="554" Top="443"/>
            <Ponto Left="573" Top="443"/>
        </Pontos>
        <Cardinalidade ID="129">
            <Bounds Height="14" Left="545" Top="431" Width="35"/>
            <DisablePainted Valor="false"/>
            <Texto>Cardinalidade_8</Texto>
            <Observacao/>
            <Dicionario/>
            <Fonte Estilo="1" Nome="Arial" Tamanho="12"/>
            <Ancorado Valor="false"/>
            <TamanhoAutmatico Valor="true"/>
            <Card Valor="0"/>
            <MovimentacaoManual Valor="false"/>
            <Papel Valor=""/>
        </Cardinalidade>
    </Ligacao>
    <Atributo ID="151">
        <Bounds Height="14" Left="440" Top="497" Width="88"/>
        <DisablePainted Valor="false"/>
        <Texto>Valor_Total</Texto>
        <Observacao/>
        <Dicionario/>
        <Fonte Estilo="1" Nome="Arial" Tamanho="12"/>
        <Ancorado Valor="false"/>
        <DirecaoFromInspector Valor="0"/>
        <Autosize Valor="true"/>
        <Identificador Valor="false"/>
        <Opcional Valor="false"/>
        <Multivalorado Valor="false"/>
        <CardMinFromString Valor="1"/>
        <CardMaxFromString Valor="n"/>
        <TipoAtributo Valor=""/>
    </Atributo>
    <Ligacao ID="152">
        <DisablePainted Valor="false"/>
        <Tag LinhaMestre="-1"/>
        <Dashed Valor="false"/>
        <Ancorado Valor="false"/>
        <TemSetaPontaA Valor="false"/>
        <TemSetaPontaB Valor="false"/>
        <SetaAberta Valor="true"/>
        <SetaLargura Valor="10"/>
        <Inteligente Valor="true"/>
        <Largura Valor="1"/>
        <Ligacoes PontaA="151" PontaB="10"/>
        <Pontos>
            <Ponto Left="436" Top="501"/>
            <Ponto Left="427" Top="501"/>
            <Ponto Left="427" Top="483"/>
            <Ponto Left="427" Top="483"/>
            <Ponto Left="427" Top="483"/>
            <Ponto Left="427" Top="473"/>
        </Pontos>
    </Ligacao>
</DIAGRAMA>
